webdriver_chauffeur
